dollarpy.py
dollarpy-0.1.1.dist-info/DESCRIPTION.rst
dollarpy-0.1.1.dist-info/METADATA
dollarpy-0.1.1.dist-info/RECORD
dollarpy-0.1.1.dist-info/WHEEL
dollarpy-0.1.1.dist-info/metadata.json
dollarpy-0.1.1.dist-info/top_level.txt
